circuitree/__init__.py
circuitree/circuitree.py
circuitree/grammar.py
circuitree/models.py
circuitree/modularity.py
circuitree/parallel.py
circuitree/parallel_utils.py
circuitree/utils.py
circuitree/viz.py
circuitree-0.11.1.dist-info/LICENSE
circuitree-0.11.1.dist-info/WHEEL
circuitree-0.11.1.dist-info/METADATA
circuitree-0.11.1.dist-info/RECORD
